{
  "id": "buttons",
  "type": "SharedSlice",
  "name": "Buttons",
  "description": "Buttons",
  "variations": [
    {
      "id": "default",
      "name": "Default",
      "docURL": "...",
      "version": "initial",
      "description": "Default",
      "imageUrl": "",
      "primary": {
        "button": {
          "type": "Link",
          "config": {
            "label": "Button",
            "placeholder": "",
            "select": null,
            "allowTargetBlank": true,
            "allowText": true,
            "repeat": true
          }
        }
      },
      "items": {}
    }
  ]
}